ShiMxnetGluonLaidongXueShenduXuexi04/README.md
ShiMxnetGluonLaidongXueShenduXuexi04/__init__.py
ShiMxnetGluonLaidongXueShenduXuexi04/__main__.py
ShiMxnetGluonLaidongXueShenduXuexi04/file.pdf
ShiMxnetGluonLaidongXueShenduXuexi04/index.html
shi_mxnet_gluon_laidong_xue_shendu_xuexi_0_4-2024.3.2.0.dist-info/METADATA
shi_mxnet_gluon_laidong_xue_shendu_xuexi_0_4-2024.3.2.0.dist-info/WHEEL
shi_mxnet_gluon_laidong_xue_shendu_xuexi_0_4-2024.3.2.0.dist-info/entry_points.txt
shi_mxnet_gluon_laidong_xue_shendu_xuexi_0_4-2024.3.2.0.dist-info/top_level.txt
shi_mxnet_gluon_laidong_xue_shendu_xuexi_0_4-2024.3.2.0.dist-info/RECORD
